duyll/__init__.py
duyll/download.py
duyll/inference.py
duyll/main.py
duyll/basicsr/test.py
duyll/basicsr/train.py
duyll/basicsr/version.py
duyll/basicsr/data/SDSD_image_dataset.py
duyll/basicsr/data/SID_image_dataset.py
duyll/basicsr/data/SMID_image_dataset.py
duyll/basicsr/data/__init__.py
duyll/basicsr/data/data_sampler.py
duyll/basicsr/data/data_util.py
duyll/basicsr/data/ffhq_dataset.py
duyll/basicsr/data/paired_image_dataset.py
duyll/basicsr/data/prefetch_dataloader.py
duyll/basicsr/data/reds_dataset.py
duyll/basicsr/data/single_image_dataset.py
duyll/basicsr/data/transforms.py
duyll/basicsr/data/util.py
duyll/basicsr/data/video_test_dataset.py
duyll/basicsr/data/vimeo90k_dataset.py
duyll/basicsr/models/__init__.py
duyll/basicsr/models/base_model.py
duyll/basicsr/models/image_restoration_model.py
duyll/basicsr/models/lr_scheduler.py
duyll/basicsr/models/archs/MST_Plus_Plus_arch.py
duyll/basicsr/models/archs/RetinexFormer_arch.py
duyll/basicsr/models/archs/__init__.py
duyll/basicsr/models/archs/arch_util.py
duyll/basicsr/models/archs/layers.py
duyll/basicsr/models/losses/__init__.py
duyll/basicsr/models/losses/loss_util.py
duyll/basicsr/models/losses/losses.py
duyll/basicsr/utils/__init__.py
duyll/basicsr/utils/bundle_submissions.py
duyll/basicsr/utils/create_lmdb.py
duyll/basicsr/utils/dist_util.py
duyll/basicsr/utils/download_util.py
duyll/basicsr/utils/face_util.py
duyll/basicsr/utils/file_client.py
duyll/basicsr/utils/flow_util.py
duyll/basicsr/utils/img_util.py
duyll/basicsr/utils/lmdb_util.py
duyll/basicsr/utils/logger.py
duyll/basicsr/utils/matlab_functions.py
duyll/basicsr/utils/misc.py
duyll/basicsr/utils/options.py
duyll-0.5.5.dist-info/METADATA
duyll-0.5.5.dist-info/WHEEL
duyll-0.5.5.dist-info/top_level.txt
duyll-0.5.5.dist-info/RECORD
