Metadata-Version: 2.1
Name: duyll
Version: 0.5.5
Requires-Dist: matplotlib
Requires-Dist: scikit-learn
Requires-Dist: scikit-image
Requires-Dist: opencv-python
Requires-Dist: yacs
Requires-Dist: joblib
Requires-Dist: natsort
Requires-Dist: h5py
Requires-Dist: tqdm
Requires-Dist: tensorboard
Requires-Dist: einops
Requires-Dist: gdown
Requires-Dist: addict
Requires-Dist: future
Requires-Dist: lmdb
Requires-Dist: numpy
Requires-Dist: pyyaml
Requires-Dist: requests
Requires-Dist: scipy
Requires-Dist: yapf
Requires-Dist: lpips
Requires-Dist: thop
Requires-Dist: timm
